btcpay/__init__.py
btcpay/client.py
btcpay/resources/__init__.py
btcpay/resources/invoices.py
btcpay/resources/pull_payments.py
btcpay_python_sdk-0.1.0.dist-info/LICENSE
btcpay_python_sdk-0.1.0.dist-info/METADATA
btcpay_python_sdk-0.1.0.dist-info/WHEEL
btcpay_python_sdk-0.1.0.dist-info/top_level.txt
btcpay_python_sdk-0.1.0.dist-info/RECORD
