Metadata-Version: 2.1
Name: btcpay-python-sdk
Version: 0.1.0
Summary: BTCPay Python SDK using the Greenfield API
Home-page: https://github.com/enfront/btcpa-python-sdk
Author: Enfront LLC
Author-email: support@enfront.io
Keywords: btcpay,bitcoin,payments,crypto
Classifier: License :: OSI Approved :: MIT License
Classifier: Intended Audience :: Developers
Classifier: Programming Language :: Python :: 3 :: Only
Classifier: Operating System :: OS Independent
Classifier: Topic :: Software Development :: Libraries :: Python Modules
Classifier: Topic :: Office/Business :: Financial
License-File: LICENSE
Requires-Dist: requests
Requires-Dist: ecdsa
